morphpiece/__init__.py
morphpiece/MorphPieceBPE/__init__.py
morphpiece/MorphPieceBPE/lookup_table_with_hash_single.pkl
morphpiece/MorphPieceBPE/single_hash_merges.txt
morphpiece/MorphPieceBPE/single_hash_vocab.json
morphpiece/MorphPieceBPE/tokenizer.py
morphpiece/MorphPieceWPE/__init__.py
morphpiece/MorphPieceWPE/lookup_dict.pkl
morphpiece/MorphPieceWPE/no_morph_vocab.txt
morphpiece/MorphPieceWPE/tokenizer.py
morphpiece/MorphPieceWPE/with_morph_vocab.txt
morphpiece-0.1.3.dist-info/METADATA
morphpiece-0.1.3.dist-info/WHEEL
morphpiece-0.1.3.dist-info/top_level.txt
morphpiece-0.1.3.dist-info/RECORD
