Metadata-Version: 2.1
Name: morphpiece
Version: 0.1.3
Summary: Morphological tokenization package
Home-page: https://github.com/MaveriQ/MorphPiece
Author: Haris Jabbar
Author-email: harisjabbar@gmail.com
License: Apache-2.0 license
Classifier: Development Status :: 4 - Beta
Classifier: Intended Audience :: Science/Research
Classifier: License :: OSI Approved :: Apache Software License
Classifier: Operating System :: POSIX :: Linux
Classifier: Programming Language :: Python :: 3
Classifier: Programming Language :: Python :: 3.7
Classifier: Programming Language :: Python :: 3.8
Classifier: Programming Language :: Python :: 3.9
Classifier: Topic :: Scientific/Engineering :: Artificial Intelligence
Requires-Python: >=3.7.0
Requires-Dist: transformers (>=4.5.0)
Requires-Dist: regex
